{
  "bank_name": "UNION",
  "account_number": "672202065729294",
  "account_holder": "DIVYA W GUPTA Home Branch",
  "statement_period": "From -20/10/2023 To 18/01/2024",
  "transactions": [
    {
      "transaction_date": "2024-01-18",
      "description": "SMS Charges",
      "amount": 19.11,
      "transaction_type": "DEBIT",
      "bank_name": "UNION",
      "account_number": "672202065729294",
      "balance": -60896.58
    },
    {
      "transaction_date": "2024-01-18",
      "description": "NEFT:CREDIT RECEIVED\nFDRLM8347953950",
      "amount": 34436.0,
      "transaction_type": "CREDIT",
      "bank_name": "UNION",
      "account_number": "672202065729294",
      "balance": -95332.58
    },
    {
      "transaction_date": "2024-01-18",
      "description": "UPIAR/740849594250/DR/Reliance/RELIANCE/SBIN/reliance@sb\ni",
      "amount": 2559.0,
      "transaction_type": "DEBIT",
      "bank_name": "UNION",
      "account_number": "672202065729294",
      "balance": -92773.58
    },
    {
      "transaction_date": "2024-01-17",
      "description": "UPIAR/724903949895/DR/Netflix/NETFLIX/HDFC/netflix@hdfcban\nk",
      "amount": 629.0,
      "transaction_type": "DEBIT",
      "bank_name": "UNION",
      "account_number": "672202065729294",
      "balance": -92144.58
    },
    {
      "transaction_date": "2024-01-17",
      "description": "UPIAB/476402487801/CR/PRIYA\nKUMAR/PRIYA/HDFC/priyak456@okhdfcbank",
      "amount": 1621.0,
      "transaction_type": "CREDIT",
      "bank_name": "UNION",
      "account_number": "672202065729294",
      "balance": -93765.58
    },
    {
      "transaction_date": "2024-01-16",
      "description": "NEFT:Int.Pd:01-01-2024 to 01-01-2024",
      "amount": 32.16,
      "transaction_type": "CREDIT",
      "bank_name": "UNION",
      "account_number": "672202065729294",
      "balance": -93797.74
    },
    {
      "transaction_date": "2024-01-16",
      "description": "NEFT:TRANSFER\nFDRLM8114327101",
      "amount": 35659.0,
      "transaction_type": "DEBIT",
      "bank_name": "UNION",
      "account_number": "672202065729294",
      "balance": -58138.74
    },
    {
      "transaction_date": "2024-01-13",
      "description": "UPIAR/610072488906/DR/BPCL Fuel/BPCL/CNRB/bpcl@canara",
      "amount": 1879.0,
      "transaction_type": "DEBIT",
      "bank_name": "UNION",
      "account_number": "672202065729294",
      "balance": -56259.74
    },
    {
      "transaction_date": "2024-01-13",
      "description": "MAND DR- BCF2442-",
      "amount": 2083.0,
      "transaction_type": "DEBIT",
      "bank_name": "UNION",
      "account_number": "672202065729294",
      "balance": -54176.74
    },
    {
      "transaction_date": "2024-01-12",
      "description": "UPIAR/469556896722/DR/Ola/OLA/ICICI/ola@icici",
      "amount": 319.0,
      "transaction_type": "DEBIT",
      "bank_name": "UNION",
      "account_number": "672202065729294",
      "balance": -53857.74
    },
    {
      "transaction_date": "2024-01-11",
      "description": "UPIAR/522499802310/DR/RAJESH\nNAIR/RAJESH/CNRB/rajeshn@okcanara",
      "amount": 5381.0,
      "transaction_type": "DEBIT",
      "bank_name": "UNION",
      "account_number": "672202065729294",
      "balance": -48476.74
    },
    {
      "transaction_date": "2024-01-11",
      "description": "UPIAB/959424325647/CR/DEEPA\nMENON/DEEPA/BARB/deepam@okbob",
      "amount": 1211.0,
      "transaction_type": "CREDIT",
      "bank_name": "UNION",
      "account_number": "672202065729294",
      "balance": -49687.74
    },
    {
      "transaction_date": "2024-01-09",
      "description": "UPIAR/513784213567/DR/Netflix/NETFLIX/HDFC/netflix@hdfcban\nk",
      "amount": 676.0,
      "transaction_type": "DEBIT",
      "bank_name": "UNION",
      "account_number": "672202065729294",
      "balance": -49011.74
    },
    {
      "transaction_date": "2024-01-08",
      "description": "UPIAR/616466289337/DR/Swiggy/SWIGGY/SBIN/swiggy@sbi",
      "amount": 438.0,
      "transaction_type": "DEBIT",
      "bank_name": "UNION",
      "account_number": "672202065729294",
      "balance": -48573.74
    },
    {
      "transaction_date": "2024-01-07",
      "description": "UPIAR/596756262941/DR/Reliance/RELIANCE/SBIN/reliance@sb\ni",
      "amount": 515.0,
      "transaction_type": "DEBIT",
      "bank_name": "UNION",
      "account_number": "672202065729294",
      "balance": -48058.74
    },
    {
      "transaction_date": "2024-01-07",
      "description": "NEFT:CREDIT RECEIVED\nFDRLM8953279248",
      "amount": 25922.0,
      "transaction_type": "CREDIT",
      "bank_name": "UNION",
      "account_number": "672202065729294",
      "balance": -73980.74
    },
    {
      "transaction_date": "2024-01-06",
      "description": "NEFT:TRANSFER\nFDRLM8285723928",
      "amount": 41441.0,
      "transaction_type": "DEBIT",
      "bank_name": "UNION",
      "account_number": "672202065729294",
      "balance": -32539.74
    },
    {
      "transaction_date": "2024-01-05",
      "description": "UPIAR/969317787597/DR/DMart/DMART/HDFC/dmart@hdfcbank",
      "amount": 2833.0,
      "transaction_type": "DEBIT",
      "bank_name": "UNION",
      "account_number": "672202065729294",
      "balance": -29706.74
    },
    {
      "transaction_date": "2023-12-28",
      "description": "ATM WDL 547963\nKOCHI",
      "amount": 2000.0,
      "transaction_type": "DEBIT",
      "bank_name": "UNION",
      "account_number": "672202065729294",
      "balance": -22442.74
    },
    {
      "transaction_date": "2023-12-28",
      "description": "UPIAR/106429529854/DR/PRIYA\nKUMAR/PRIYA/HDFC/priyak456@okhdfcbank",
      "amount": 9471.0,
      "transaction_type": "DEBIT",
      "bank_name": "UNION",
      "account_number": "672202065729294",
      "balance": -12971.74
    },
    {
      "transaction_date": "2023-12-27",
      "description": "NEFT:TRANSFER\nFDRLM8089686783",
      "amount": 49087.0,
      "transaction_type": "DEBIT",
      "bank_name": "UNION",
      "account_number": "672202065729294",
      "balance": 36115.26
    },
    {
      "transaction_date": "2023-12-26",
      "description": "UPIAR/744655731006/DR/BPCL Fuel/BPCL/CNRB/bpcl@canara",
      "amount": 1663.0,
      "transaction_type": "DEBIT",
      "bank_name": "UNION",
      "account_number": "672202065729294",
      "balance": 37778.26
    },
    {
      "transaction_date": "2023-12-25",
      "description": "SMS Charges",
      "amount": 16.38,
      "transaction_type": "DEBIT",
      "bank_name": "UNION",
      "account_number": "672202065729294",
      "balance": 37794.64
    },
    {
      "transaction_date": "2023-12-25",
      "description": "NEFT:TRANSFER\nFDRLM8797641540",
      "amount": 48370.0,
      "transaction_type": "DEBIT",
      "bank_name": "UNION",
      "account_number": "672202065729294",
      "balance": 86164.64
    },
    {
      "transaction_date": "2023-12-24",
      "description": "NEFT:SALARY CREDIT\nFDRLM8786030793",
      "amount": 51448.0,
      "transaction_type": "CREDIT",
      "bank_name": "UNION",
      "account_number": "672202065729294",
      "balance": 34716.64
    },
    {
      "transaction_date": "2023-12-23",
      "description": "NEFT:CREDIT RECEIVED\nFDRLM8146292775",
      "amount": 6986.0,
      "transaction_type": "CREDIT",
      "bank_name": "UNION",
      "account_number": "672202065729294",
      "balance": 27730.64
    },
    {
      "transaction_date": "2023-12-23",
      "description": "UPIAR/833751490600/DR/Swiggy/SWIGGY/SBIN/swiggy@sbi",
      "amount": 603.0,
      "transaction_type": "DEBIT",
      "bank_name": "UNION",
      "account_number": "672202065729294",
      "balance": 28333.64
    },
    {
      "transaction_date": "2023-12-23",
      "description": "NEFT:Int.Pd:01-10-2023 to 01-12-2023",
      "amount": 48.77,
      "transaction_type": "CREDIT",
      "bank_name": "UNION",
      "account_number": "672202065729294",
      "balance": 28284.87
    },
    {
      "transaction_date": "2023-12-23",
      "description": "UPIAR/334279833003/DR/RAHUL\nSHARMA/RAHUL/SBIN/rahul123@oksbi",
      "amount": 3226.0,
      "transaction_type": "DEBIT",
      "bank_name": "UNION",
      "account_number": "672202065729294",
      "balance": 31510.87
    },
    {
      "transaction_date": "2023-12-22",
      "description": "UPIAB/393455499361/CR/SNEHA\nREDDY/SNEHA/AXIS/snehar@okaxis",
      "amount": 1865.0,
      "transaction_type": "CREDIT",
      "bank_name": "UNION",
      "account_number": "672202065729294",
      "balance": 29645.87
    },
    {
      "transaction_date": "2023-12-22",
      "description": "UPIAR/936766708552/DR/PhonePe/PHONEPE/YESB/phonepe@\nybl",
      "amount": 480.0,
      "transaction_type": "DEBIT",
      "bank_name": "UNION",
      "account_number": "672202065729294",
      "balance": 30125.87
    },
    {
      "transaction_date": "2023-12-21",
      "description": "NEFT:Int.Pd:01-10-2023 to 01-12-2023",
      "amount": 27.08,
      "transaction_type": "CREDIT",
      "bank_name": "UNION",
      "account_number": "672202065729294",
      "balance": 30098.79
    },
    {
      "transaction_date": "2023-12-20",
      "description": "UPIAR/566313223528/DR/Reliance/RELIANCE/SBIN/reliance@sb\ni",
      "amount": 2684.0,
      "transaction_type": "DEBIT",
      "bank_name": "UNION",
      "account_number": "672202065729294",
      "balance": 32782.79
    },
    {
      "transaction_date": "2023-12-20",
      "description": "UPIAR/184359094453/DR/Netflix/NETFLIX/HDFC/netflix@hdfcban\nk",
      "amount": 788.0,
      "transaction_type": "DEBIT",
      "bank_name": "UNION",
      "account_number": "672202065729294",
      "balance": 33570.79
    },
    {
      "transaction_date": "2023-12-20",
      "description": "UPIAR/316116430562/DR/PhonePe/PHONEPE/YESB/phonepe@\nybl",
      "amount": 1875.0,
      "transaction_type": "DEBIT",
      "bank_name": "UNION",
      "account_number": "672202065729294",
      "balance": 35445.79
    },
    {
      "transaction_date": "2023-12-20",
      "description": "UPIAB/978780188604/CR/SNEHA\nREDDY/SNEHA/AXIS/snehar@okaxis",
      "amount": 2230.0,
      "transaction_type": "CREDIT",
      "bank_name": "UNION",
      "account_number": "672202065729294",
      "balance": 33215.79
    },
    {
      "transaction_date": "2023-12-19",
      "description": "UPIAR/752893414071/DR/Swiggy/SWIGGY/SBIN/swiggy@sbi",
      "amount": 660.0,
      "transaction_type": "DEBIT",
      "bank_name": "UNION",
      "account_number": "672202065729294",
      "balance": 33875.79
    },
    {
      "transaction_date": "2023-12-19",
      "description": "UPIAR/371270433991/DR/Zomato/ZOMATO/HDFC/zomato@hdfc\nbank",
      "amount": 419.0,
      "transaction_type": "DEBIT",
      "bank_name": "UNION",
      "account_number": "672202065729294",
      "balance": 34294.79
    },
    {
      "transaction_date": "2023-12-19",
      "description": "UPIAR/666629047229/DR/Flipkart/FLIPKART/AXIS/flipkart@axisb\nank",
      "amount": 5892.0,
      "transaction_type": "DEBIT",
      "bank_name": "UNION",
      "account_number": "672202065729294",
      "balance": 40186.79
    },
    {
      "transaction_date": "2023-12-18",
      "description": "NEFT:Int.Pd:01-10-2023 to 01-12-2023",
      "amount": 39.25,
      "transaction_type": "CREDIT",
      "bank_name": "UNION",
      "account_number": "672202065729294",
      "balance": 40147.54
    },
    {
      "transaction_date": "2023-12-17",
      "description": "UPIAR/101515273394/DR/Indian\nOil/INDIANOIL/YESB/indianoil@ybl",
      "amount": 1691.0,
      "transaction_type": "DEBIT",
      "bank_name": "UNION",
      "account_number": "672202065729294",
      "balance": 41838.54
    },
    {
      "transaction_date": "2023-12-17",
      "description": "UPIAR/845839385291/DR/Netflix/NETFLIX/HDFC/netflix@hdfcban\nk",
      "amount": 559.0,
      "transaction_type": "DEBIT",
      "bank_name": "UNION",
      "account_number": "672202065729294",
      "balance": 42397.54
    },
    {
      "transaction_date": "2023-12-17",
      "description": "UPIAR/392486324610/DR/Uber/UBER/UTIB/uber@axisbank",
      "amount": 333.0,
      "transaction_type": "DEBIT",
      "bank_name": "UNION",
      "account_number": "672202065729294",
      "balance": 42730.54
    },
    {
      "transaction_date": "2023-12-17",
      "description": "ATM WDL 200542\nKANNUR",
      "amount": 3000.0,
      "transaction_type": "DEBIT",
      "bank_name": "UNION",
      "account_number": "672202065729294",
      "balance": 45730.54
    },
    {
      "transaction_date": "2023-12-16",
      "description": "UPIAR/160577343077/DR/Indian\nOil/INDIANOIL/YESB/indianoil@ybl",
      "amount": 1520.0,
      "transaction_type": "DEBIT",
      "bank_name": "UNION",
      "account_number": "672202065729294",
      "balance": 47250.54
    },
    {
      "transaction_date": "2023-12-16",
      "description": "NEFT:Int.Pd:01-10-2023 to 01-12-2023",
      "amount": 34.68,
      "transaction_type": "CREDIT",
      "bank_name": "UNION",
      "account_number": "672202065729294",
      "balance": 47215.86
    },
    {
      "transaction_date": "2023-12-16",
      "description": "UPIAR/107334967198/DR/BookMyShow/BOOKMYSHOW/ICICI/b\nookmyshow@icici",
      "amount": 421.0,
      "transaction_type": "DEBIT",
      "bank_name": "UNION",
      "account_number": "672202065729294",
      "balance": 47636.86
    },
    {
      "transaction_date": "2023-12-16",
      "description": "UPIAR/116483084374/DR/Zomato/ZOMATO/HDFC/zomato@hdfc\nbank",
      "amount": 837.0,
      "transaction_type": "DEBIT",
      "bank_name": "UNION",
      "account_number": "672202065729294",
      "balance": 48473.86
    },
    {
      "transaction_date": "2023-12-15",
      "description": "UPIAR/498406281035/DR/Zomato/ZOMATO/HDFC/zomato@hdfc\nbank",
      "amount": 751.0,
      "transaction_type": "DEBIT",
      "bank_name": "UNION",
      "account_number": "672202065729294",
      "balance": 49224.86
    },
    {
      "transaction_date": "2023-12-15",
      "description": "UPIAB/860241039318/CR/RAJESH\nNAIR/RAJESH/CNRB/rajeshn@okcanara",
      "amount": 4826.0,
      "transaction_type": "CREDIT",
      "bank_name": "UNION",
      "account_number": "672202065729294",
      "balance": 44398.86
    },
    {
      "transaction_date": "2023-12-14",
      "description": "NEFT:Int.Pd:01-10-2023 to 01-12-2023",
      "amount": 40.13,
      "transaction_type": "CREDIT",
      "bank_name": "UNION",
      "account_number": "672202065729294",
      "balance": 44358.73
    },
    {
      "transaction_date": "2023-12-14",
      "description": "ATM WDL 716853\nKASARAGOD",
      "amount": 1000.0,
      "transaction_type": "DEBIT",
      "bank_name": "UNION",
      "account_number": "672202065729294",
      "balance": 45358.73
    },
    {
      "transaction_date": "2023-12-13",
      "description": "UPIAR/194483036275/DR/Indian\nOil/INDIANOIL/YESB/indianoil@ybl",
      "amount": 1147.0,
      "transaction_type": "DEBIT",
      "bank_name": "UNION",
      "account_number": "672202065729294",
      "balance": 46505.73
    },
    {
      "transaction_date": "2023-12-13",
      "description": "UPIAR/924410953260/DR/Paytm/PAYTM/PYTM/paytm@paytm",
      "amount": 324.0,
      "transaction_type": "DEBIT",
      "bank_name": "UNION",
      "account_number": "672202065729294",
      "balance": 46829.73
    },
    {
      "transaction_date": "2023-12-12",
      "description": "UPIAB/791068490005/CR/SNEHA\nREDDY/SNEHA/AXIS/snehar@okaxis",
      "amount": 6895.0,
      "transaction_type": "CREDIT",
      "bank_name": "UNION",
      "account_number": "672202065729294",
      "balance": 39934.73
    },
    {
      "transaction_date": "2023-12-12",
      "description": "UPIAR/293096843298/DR/Zomato/ZOMATO/HDFC/zomato@hdfc\nbank",
      "amount": 389.0,
      "transaction_type": "DEBIT",
      "bank_name": "UNION",
      "account_number": "672202065729294",
      "balance": 40323.73
    },
    {
      "transaction_date": "2023-12-12",
      "description": "UPIAR/567370839139/DR/SNEHA\nREDDY/SNEHA/AXIS/snehar@okaxis",
      "amount": 9389.0,
      "transaction_type": "DEBIT",
      "bank_name": "UNION",
      "account_number": "672202065729294",
      "balance": 49712.73
    },
    {
      "transaction_date": "2023-12-12",
      "description": "UPIAB/418885043623/CR/DEEPA\nMENON/DEEPA/BARB/deepam@okbob",
      "amount": 896.0,
      "transaction_type": "CREDIT",
      "bank_name": "UNION",
      "account_number": "672202065729294",
      "balance": 48816.73
    },
    {
      "transaction_date": "2023-12-11",
      "description": "UPIAR/437929431046/DR/KAVITA\nVERMA/KAVITA/KLGB/kavitav@okklgb",
      "amount": 8188.0,
      "transaction_type": "DEBIT",
      "bank_name": "UNION",
      "account_number": "672202065729294",
      "balance": 57004.73
    },
    {
      "transaction_date": "2023-12-11",
      "description": "UPIAR/112291936147/DR/Flipkart/FLIPKART/AXIS/flipkart@axisb\nank",
      "amount": 2723.0,
      "transaction_type": "DEBIT",
      "bank_name": "UNION",
      "account_number": "672202065729294",
      "balance": 59727.73
    },
    {
      "transaction_date": "2023-12-11",
      "description": "UPIAB/424314321667/CR/DEEPA\nMENON/DEEPA/BARB/deepam@okbob",
      "amount": 5346.0,
      "transaction_type": "CREDIT",
      "bank_name": "UNION",
      "account_number": "672202065729294",
      "balance": 54381.73
    },
    {
      "transaction_date": "2023-12-11",
      "description": "UPIAR/666066343402/DR/Google\nPlay/GOOGLEPLAY/UTIB/goog-payment@okaxis",
      "amount": 418.0,
      "transaction_type": "DEBIT",
      "bank_name": "UNION",
      "account_number": "672202065729294",
      "balance": 54799.73
    },
    {
      "transaction_date": "2023-12-10",
      "description": "UPIAR/793372356771/DR/DMart/DMART/HDFC/dmart@hdfcbank",
      "amount": 1252.0,
      "transaction_type": "DEBIT",
      "bank_name": "UNION",
      "account_number": "672202065729294",
      "balance": 56051.73
    },
    {
      "transaction_date": "2023-12-09",
      "description": "UPIAR/698934768305/DR/Google\nPlay/GOOGLEPLAY/UTIB/goog-payment@okaxis",
      "amount": 906.0,
      "transaction_type": "DEBIT",
      "bank_name": "UNION",
      "account_number": "672202065729294",
      "balance": 56957.73
    },
    {
      "transaction_date": "2023-12-07",
      "description": "NEFT:CREDIT RECEIVED\nFDRLM8964819899",
      "amount": 40923.0,
      "transaction_type": "CREDIT",
      "bank_name": "UNION",
      "account_number": "672202065729294",
      "balance": 16034.73
    },
    {
      "transaction_date": "2023-12-07",
      "description": "UPIAR/105689598142/DR/Paytm/PAYTM/PYTM/paytm@paytm",
      "amount": 1135.0,
      "transaction_type": "DEBIT",
      "bank_name": "UNION",
      "account_number": "672202065729294",
      "balance": 17169.73
    },
    {
      "transaction_date": "2023-12-06",
      "description": "ATM WDL 138053\nKANNUR",
      "amount": 2000.0,
      "transaction_type": "DEBIT",
      "bank_name": "UNION",
      "account_number": "672202065729294",
      "balance": 19169.73
    },
    {
      "transaction_date": "2023-12-05",
      "description": "UPIAR/154392016041/DR/DMart/DMART/HDFC/dmart@hdfcbank",
      "amount": 2401.0,
      "transaction_type": "DEBIT",
      "bank_name": "UNION",
      "account_number": "672202065729294",
      "balance": 21570.73
    },
    {
      "transaction_date": "2023-12-05",
      "description": "UPIAR/523705502889/DR/SNEHA\nREDDY/SNEHA/AXIS/snehar@okaxis",
      "amount": 3000.0,
      "transaction_type": "DEBIT",
      "bank_name": "UNION",
      "account_number": "672202065729294",
      "balance": 24570.73
    },
    {
      "transaction_date": "2023-12-04",
      "description": "UPIAR/940819798208/DR/Swiggy/SWIGGY/SBIN/swiggy@sbi",
      "amount": 556.0,
      "transaction_type": "DEBIT",
      "bank_name": "UNION",
      "account_number": "672202065729294",
      "balance": 25126.73
    },
    {
      "transaction_date": "2023-12-03",
      "description": "ATM WDL 526644\nKOCHI",
      "amount": 500.0,
      "transaction_type": "DEBIT",
      "bank_name": "UNION",
      "account_number": "672202065729294",
      "balance": 25626.73
    },
    {
      "transaction_date": "2023-12-03",
      "description": "ATM WDL 917745\nKOCHI",
      "amount": 5000.0,
      "transaction_type": "DEBIT",
      "bank_name": "UNION",
      "account_number": "672202065729294",
      "balance": 30626.73
    },
    {
      "transaction_date": "2023-12-02",
      "description": "UPIAR/717444331231/DR/DMart/DMART/HDFC/dmart@hdfcbank",
      "amount": 2424.0,
      "transaction_type": "DEBIT",
      "bank_name": "UNION",
      "account_number": "672202065729294",
      "balance": 33050.73
    },
    {
      "transaction_date": "2023-12-01",
      "description": "UPIAR/824609084958/DR/Reliance/RELIANCE/SBIN/reliance@sb\ni",
      "amount": 2975.0,
      "transaction_type": "DEBIT",
      "bank_name": "UNION",
      "account_number": "672202065729294",
      "balance": 36025.73
    },
    {
      "transaction_date": "2023-12-01",
      "description": "UPIAR/871326091875/DR/Zomato/ZOMATO/HDFC/zomato@hdfc\nbank",
      "amount": 457.0,
      "transaction_type": "DEBIT",
      "bank_name": "UNION",
      "account_number": "672202065729294",
      "balance": 36482.73
    },
    {
      "transaction_date": "2023-11-30",
      "description": "UPIAR/491097164896/DR/Uber/UBER/UTIB/uber@axisbank",
      "amount": 212.0,
      "transaction_type": "DEBIT",
      "bank_name": "UNION",
      "account_number": "672202065729294",
      "balance": 36694.73
    },
    {
      "transaction_date": "2023-11-30",
      "description": "NEFT:Int.Pd:01-10-2023 to 01-11-2023",
      "amount": 28.88,
      "transaction_type": "CREDIT",
      "bank_name": "UNION",
      "account_number": "672202065729294",
      "balance": 36665.85
    },
    {
      "transaction_date": "2023-11-29",
      "description": "UPIAR/437340387530/DR/Flipkart/FLIPKART/AXIS/flipkart@axisb\nank",
      "amount": 5294.0,
      "transaction_type": "DEBIT",
      "bank_name": "UNION",
      "account_number": "672202065729294",
      "balance": 41959.85
    },
    {
      "transaction_date": "2023-11-29",
      "description": "UPIAR/710771878327/DR/RAJESH\nNAIR/RAJESH/CNRB/rajeshn@okcanara",
      "amount": 9722.0,
      "transaction_type": "DEBIT",
      "bank_name": "UNION",
      "account_number": "672202065729294",
      "balance": 51681.85
    },
    {
      "transaction_date": "2023-11-28",
      "description": "NEFT:CREDIT RECEIVED\nFDRLM8891289890",
      "amount": 46888.0,
      "transaction_type": "CREDIT",
      "bank_name": "UNION",
      "account_number": "672202065729294",
      "balance": 4793.85
    },
    {
      "transaction_date": "2023-11-28",
      "description": "UPIAR/229510819712/DR/Netflix/NETFLIX/HDFC/netflix@hdfcban\nk",
      "amount": 254.0,
      "transaction_type": "DEBIT",
      "bank_name": "UNION",
      "account_number": "672202065729294",
      "balance": 5047.85
    },
    {
      "transaction_date": "2023-11-27",
      "description": "ATM WDL 807787\nKANNUR",
      "amount": 2000.0,
      "transaction_type": "DEBIT",
      "bank_name": "UNION",
      "account_number": "672202065729294",
      "balance": 7047.85
    },
    {
      "transaction_date": "2023-11-25",
      "description": "UPIAR/742179236207/DR/Uber/UBER/UTIB/uber@axisbank",
      "amount": 393.0,
      "transaction_type": "DEBIT",
      "bank_name": "UNION",
      "account_number": "672202065729294",
      "balance": 7440.85
    },
    {
      "transaction_date": "2023-11-24",
      "description": "ATM WDL 487030\nKASARAGOD",
      "amount": 2000.0,
      "transaction_type": "DEBIT",
      "bank_name": "UNION",
      "account_number": "672202065729294",
      "balance": 9440.85
    },
    {
      "transaction_date": "2023-11-24",
      "description": "UPIAR/483142255478/DR/Reliance/RELIANCE/SBIN/reliance@sb\ni",
      "amount": 1278.0,
      "transaction_type": "DEBIT",
      "bank_name": "UNION",
      "account_number": "672202065729294",
      "balance": 10718.85
    },
    {
      "transaction_date": "2023-11-24",
      "description": "UPIAR/451190812369/DR/Google\nPlay/GOOGLEPLAY/UTIB/goog-payment@okaxis",
      "amount": 343.0,
      "transaction_type": "DEBIT",
      "bank_name": "UNION",
      "account_number": "672202065729294",
      "balance": 11061.85
    },
    {
      "transaction_date": "2023-11-23",
      "description": "UPIAR/358837675633/DR/Flipkart/FLIPKART/AXIS/flipkart@axisb\nank",
      "amount": 2486.0,
      "transaction_type": "DEBIT",
      "bank_name": "UNION",
      "account_number": "672202065729294",
      "balance": 13547.85
    },
    {
      "transaction_date": "2023-11-22",
      "description": "UPIAR/637436662378/DR/Netflix/NETFLIX/HDFC/netflix@hdfcban\nk",
      "amount": 779.0,
      "transaction_type": "DEBIT",
      "bank_name": "UNION",
      "account_number": "672202065729294",
      "balance": 14326.85
    },
    {
      "transaction_date": "2023-11-21",
      "description": "ATM WDL 449537\nKANNUR",
      "amount": 500.0,
      "transaction_type": "DEBIT",
      "bank_name": "UNION",
      "account_number": "672202065729294",
      "balance": 14826.85
    },
    {
      "transaction_date": "2023-11-21",
      "description": "General Charges Recovery",
      "amount": 101.19,
      "transaction_type": "DEBIT",
      "bank_name": "UNION",
      "account_number": "672202065729294",
      "balance": 14928.04
    },
    {
      "transaction_date": "2023-11-21",
      "description": "MAND DR- BCF2442-",
      "amount": 2083.0,
      "transaction_type": "DEBIT",
      "bank_name": "UNION",
      "account_number": "672202065729294",
      "balance": 17011.04
    },
    {
      "transaction_date": "2023-11-20",
      "description": "ATM WDL 279323\nKASARAGOD",
      "amount": 1000.0,
      "transaction_type": "DEBIT",
      "bank_name": "UNION",
      "account_number": "672202065729294",
      "balance": 18011.04
    },
    {
      "transaction_date": "2023-11-20",
      "description": "General Charges Recovery",
      "amount": 124.14,
      "transaction_type": "DEBIT",
      "bank_name": "UNION",
      "account_number": "672202065729294",
      "balance": 18135.18
    },
    {
      "transaction_date": "2023-11-19",
      "description": "UPIAR/109204612485/DR/VIJAY\nSINGH/VIJAY/FDRL/vijays@okfederal",
      "amount": 9454.0,
      "transaction_type": "DEBIT",
      "bank_name": "UNION",
      "account_number": "672202065729294",
      "balance": 27589.18
    },
    {
      "transaction_date": "2023-11-18",
      "description": "UPIAB/930422867700/CR/KAVITA\nVERMA/KAVITA/KLGB/kavitav@okklgb",
      "amount": 6042.0,
      "transaction_type": "CREDIT",
      "bank_name": "UNION",
      "account_number": "672202065729294",
      "balance": 21547.18
    },
    {
      "transaction_date": "2023-11-18",
      "description": "UPIAB/413994359159/CR/SNEHA\nREDDY/SNEHA/AXIS/snehar@okaxis",
      "amount": 9137.0,
      "transaction_type": "CREDIT",
      "bank_name": "UNION",
      "account_number": "672202065729294",
      "balance": 12410.18
    },
    {
      "transaction_date": "2023-11-17",
      "description": "General Charges Recovery",
      "amount": 161.03,
      "transaction_type": "DEBIT",
      "bank_name": "UNION",
      "account_number": "672202065729294",
      "balance": 12571.21
    },
    {
      "transaction_date": "2023-11-17",
      "description": "ATM WDL 490162\nKANNUR",
      "amount": 2000.0,
      "transaction_type": "DEBIT",
      "bank_name": "UNION",
      "account_number": "672202065729294",
      "balance": 14571.21
    },
    {
      "transaction_date": "2023-11-16",
      "description": "UPIAR/665913300520/DR/Reliance/RELIANCE/SBIN/reliance@sb\ni",
      "amount": 3700.0,
      "transaction_type": "DEBIT",
      "bank_name": "UNION",
      "account_number": "672202065729294",
      "balance": 18271.21
    },
    {
      "transaction_date": "2023-11-16",
      "description": "UPIAB/783443505498/CR/RAHUL\nSHARMA/RAHUL/SBIN/rahul123@oksbi",
      "amount": 1746.0,
      "transaction_type": "CREDIT",
      "bank_name": "UNION",
      "account_number": "672202065729294",
      "balance": 16525.21
    },
    {
      "transaction_date": "2023-11-16",
      "description": "UPIAR/403667873854/DR/Google\nPlay/GOOGLEPLAY/UTIB/goog-payment@okaxis",
      "amount": 637.0,
      "transaction_type": "DEBIT",
      "bank_name": "UNION",
      "account_number": "672202065729294",
      "balance": 17162.21
    },
    {
      "transaction_date": "2023-11-16",
      "description": "NEFT:CREDIT RECEIVED\nFDRLM8415559769",
      "amount": 9325.0,
      "transaction_type": "CREDIT",
      "bank_name": "UNION",
      "account_number": "672202065729294",
      "balance": 7837.21
    },
    {
      "transaction_date": "2023-11-14",
      "description": "ATM WDL 612198\nKASARAGOD",
      "amount": 5000.0,
      "transaction_type": "DEBIT",
      "bank_name": "UNION",
      "account_number": "672202065729294",
      "balance": 12837.21
    },
    {
      "transaction_date": "2023-11-13",
      "description": "UPIAB/575002918192/CR/PRIYA\nKUMAR/PRIYA/HDFC/priyak456@okhdfcbank",
      "amount": 3884.0,
      "transaction_type": "CREDIT",
      "bank_name": "UNION",
      "account_number": "672202065729294",
      "balance": 8953.21
    },
    {
      "transaction_date": "2023-11-12",
      "description": "UPIAR/421274817153/DR/DMart/DMART/HDFC/dmart@hdfcbank",
      "amount": 1679.0,
      "transaction_type": "DEBIT",
      "bank_name": "UNION",
      "account_number": "672202065729294",
      "balance": 10632.21
    },
    {
      "transaction_date": "2023-11-12",
      "description": "UPIAR/762190131303/DR/Swiggy/SWIGGY/SBIN/swiggy@sbi",
      "amount": 556.0,
      "transaction_type": "DEBIT",
      "bank_name": "UNION",
      "account_number": "672202065729294",
      "balance": 11188.21
    },
    {
      "transaction_date": "2023-11-12",
      "description": "UPIAR/822647369237/DR/Ola/OLA/ICICI/ola@icici",
      "amount": 63.0,
      "transaction_type": "DEBIT",
      "bank_name": "UNION",
      "account_number": "672202065729294",
      "balance": 11251.21
    },
    {
      "transaction_date": "2023-11-10",
      "description": "UPIAR/573855809138/DR/BookMyShow/BOOKMYSHOW/ICICI/b\nookmyshow@icici",
      "amount": 261.0,
      "transaction_type": "DEBIT",
      "bank_name": "UNION",
      "account_number": "672202065729294",
      "balance": 11512.21
    },
    {
      "transaction_date": "2023-11-09",
      "description": "UPIAR/944247384672/DR/Google\nPlay/GOOGLEPLAY/UTIB/goog-payment@okaxis",
      "amount": 574.0,
      "transaction_type": "DEBIT",
      "bank_name": "UNION",
      "account_number": "672202065729294",
      "balance": 12086.21
    },
    {
      "transaction_date": "2023-11-09",
      "description": "UPIAR/294660925943/DR/VIJAY\nSINGH/VIJAY/FDRL/vijays@okfederal",
      "amount": 9858.0,
      "transaction_type": "DEBIT",
      "bank_name": "UNION",
      "account_number": "672202065729294",
      "balance": 21944.21
    },
    {
      "transaction_date": "2023-11-08",
      "description": "UPIAB/616363346023/CR/VIJAY\nSINGH/VIJAY/FDRL/vijays@okfederal",
      "amount": 9081.0,
      "transaction_type": "CREDIT",
      "bank_name": "UNION",
      "account_number": "672202065729294",
      "balance": 12863.21
    },
    {
      "transaction_date": "2023-11-08",
      "description": "NEFT:TRANSFER\nFDRLM8162366729",
      "amount": 6514.0,
      "transaction_type": "DEBIT",
      "bank_name": "UNION",
      "account_number": "672202065729294",
      "balance": 19377.21
    },
    {
      "transaction_date": "2023-11-07",
      "description": "UPIAB/231515361041/CR/KAVITA\nVERMA/KAVITA/KLGB/kavitav@okklgb",
      "amount": 1807.0,
      "transaction_type": "CREDIT",
      "bank_name": "UNION",
      "account_number": "672202065729294",
      "balance": 17570.21
    },
    {
      "transaction_date": "2023-11-07",
      "description": "UPIAR/964590703466/DR/Swiggy/SWIGGY/SBIN/swiggy@sbi",
      "amount": 616.0,
      "transaction_type": "DEBIT",
      "bank_name": "UNION",
      "account_number": "672202065729294",
      "balance": 18186.21
    },
    {
      "transaction_date": "2023-11-07",
      "description": "ATM WDL 180304\nKANNUR",
      "amount": 3000.0,
      "transaction_type": "DEBIT",
      "bank_name": "UNION",
      "account_number": "672202065729294",
      "balance": 21186.21
    },
    {
      "transaction_date": "2023-11-05",
      "description": "UPIAB/841432957287/CR/SNEHA\nREDDY/SNEHA/AXIS/snehar@okaxis",
      "amount": 1477.0,
      "transaction_type": "CREDIT",
      "bank_name": "UNION",
      "account_number": "672202065729294",
      "balance": 19709.21
    },
    {
      "transaction_date": "2023-11-04",
      "description": "ATM WDL 108236\nKOCHI",
      "amount": 1000.0,
      "transaction_type": "DEBIT",
      "bank_name": "UNION",
      "account_number": "672202065729294",
      "balance": 20709.21
    },
    {
      "transaction_date": "2023-11-03",
      "description": "NEFT:Int.Pd:01-10-2023 to 01-11-2023",
      "amount": 22.06,
      "transaction_type": "CREDIT",
      "bank_name": "UNION",
      "account_number": "672202065729294",
      "balance": 20687.15
    },
    {
      "transaction_date": "2023-11-03",
      "description": "NEFT:Int.Pd:01-10-2023 to 01-11-2023",
      "amount": 43.56,
      "transaction_type": "CREDIT",
      "bank_name": "UNION",
      "account_number": "672202065729294",
      "balance": 20643.59
    },
    {
      "transaction_date": "2023-11-02",
      "description": "UPIAR/197053462679/DR/Flipkart/FLIPKART/AXIS/flipkart@axisb\nank",
      "amount": 3070.0,
      "transaction_type": "DEBIT",
      "bank_name": "UNION",
      "account_number": "672202065729294",
      "balance": 23713.59
    },
    {
      "transaction_date": "2023-11-02",
      "description": "UPIAR/762687016968/DR/DMart/DMART/HDFC/dmart@hdfcbank",
      "amount": 1089.0,
      "transaction_type": "DEBIT",
      "bank_name": "UNION",
      "account_number": "672202065729294",
      "balance": 24802.59
    },
    {
      "transaction_date": "2023-11-01",
      "description": "UPIAB/550976326800/CR/SNEHA\nREDDY/SNEHA/AXIS/snehar@okaxis",
      "amount": 9846.0,
      "transaction_type": "CREDIT",
      "bank_name": "UNION",
      "account_number": "672202065729294",
      "balance": 14956.59
    },
    {
      "transaction_date": "2023-11-01",
      "description": "UPIAR/187272287136/DR/RAJESH\nNAIR/RAJESH/CNRB/rajeshn@okcanara",
      "amount": 9784.0,
      "transaction_type": "DEBIT",
      "bank_name": "UNION",
      "account_number": "672202065729294",
      "balance": 24740.59
    },
    {
      "transaction_date": "2023-10-30",
      "description": "NEFT:SALARY CREDIT\nFDRLM8125511188",
      "amount": 38848.0,
      "transaction_type": "CREDIT",
      "bank_name": "UNION",
      "account_number": "672202065729294",
      "balance": -14107.41
    },
    {
      "transaction_date": "2023-10-30",
      "description": "UPIAR/292003187820/DR/AMIT\nPATEL/AMIT/ICICI/amitp789@okicici",
      "amount": 6735.0,
      "transaction_type": "DEBIT",
      "bank_name": "UNION",
      "account_number": "672202065729294",
      "balance": -7372.41
    },
    {
      "transaction_date": "2023-10-30",
      "description": "UPIAR/446674792814/DR/KAVITA\nVERMA/KAVITA/KLGB/kavitav@okklgb",
      "amount": 7968.0,
      "transaction_type": "DEBIT",
      "bank_name": "UNION",
      "account_number": "672202065729294",
      "balance": 595.59
    },
    {
      "transaction_date": "2023-10-30",
      "description": "UPIAR/603819601099/DR/BookMyShow/BOOKMYSHOW/ICICI/b\nookmyshow@icici",
      "amount": 435.0,
      "transaction_type": "DEBIT",
      "bank_name": "UNION",
      "account_number": "672202065729294",
      "balance": 1030.59
    },
    {
      "transaction_date": "2023-10-29",
      "description": "UPIAB/201623900181/CR/AMIT\nPATEL/AMIT/ICICI/amitp789@okicici",
      "amount": 3574.0,
      "transaction_type": "CREDIT",
      "bank_name": "UNION",
      "account_number": "672202065729294",
      "balance": -2543.41
    },
    {
      "transaction_date": "2023-10-28",
      "description": "UPIAR/666350270791/DR/Swiggy/SWIGGY/SBIN/swiggy@sbi",
      "amount": 676.0,
      "transaction_type": "DEBIT",
      "bank_name": "UNION",
      "account_number": "672202065729294",
      "balance": -1867.41
    },
    {
      "transaction_date": "2023-10-27",
      "description": "UPIAR/912167969027/DR/VIJAY\nSINGH/VIJAY/FDRL/vijays@okfederal",
      "amount": 6214.0,
      "transaction_type": "DEBIT",
      "bank_name": "UNION",
      "account_number": "672202065729294",
      "balance": 4346.59
    },
    {
      "transaction_date": "2023-10-27",
      "description": "MAND DR- BCF2442-",
      "amount": 2083.0,
      "transaction_type": "DEBIT",
      "bank_name": "UNION",
      "account_number": "672202065729294",
      "balance": 6429.59
    },
    {
      "transaction_date": "2023-10-27",
      "description": "UPIAB/105458289189/CR/SNEHA\nREDDY/SNEHA/AXIS/snehar@okaxis",
      "amount": 6191.0,
      "transaction_type": "CREDIT",
      "bank_name": "UNION",
      "account_number": "672202065729294",
      "balance": 238.59
    },
    {
      "transaction_date": "2023-10-26",
      "description": "UPIAB/273871408848/CR/RAHUL\nSHARMA/RAHUL/SBIN/rahul123@oksbi",
      "amount": 1445.0,
      "transaction_type": "CREDIT",
      "bank_name": "UNION",
      "account_number": "672202065729294",
      "balance": -1206.41
    },
    {
      "transaction_date": "2023-10-24",
      "description": "UPIAR/376863408413/DR/SNEHA\nREDDY/SNEHA/AXIS/snehar@okaxis",
      "amount": 1977.0,
      "transaction_type": "DEBIT",
      "bank_name": "UNION",
      "account_number": "672202065729294",
      "balance": 770.59
    },
    {
      "transaction_date": "2023-10-24",
      "description": "ATM WDL 542578\nKANNUR",
      "amount": 500.0,
      "transaction_type": "DEBIT",
      "bank_name": "UNION",
      "account_number": "672202065729294",
      "balance": 1270.59
    },
    {
      "transaction_date": "2023-10-24",
      "description": "UPIAR/321410617763/DR/KAVITA\nVERMA/KAVITA/KLGB/kavitav@okklgb",
      "amount": 1056.0,
      "transaction_type": "DEBIT",
      "bank_name": "UNION",
      "account_number": "672202065729294",
      "balance": 2326.59
    },
    {
      "transaction_date": "2023-10-23",
      "description": "UPIAR/994937103669/DR/Ola/OLA/ICICI/ola@icici",
      "amount": 439.0,
      "transaction_type": "DEBIT",
      "bank_name": "UNION",
      "account_number": "672202065729294",
      "balance": 2765.59
    },
    {
      "transaction_date": "2023-10-23",
      "description": "UPIAR/312664734432/DR/DMart/DMART/HDFC/dmart@hdfcbank",
      "amount": 2531.0,
      "transaction_type": "DEBIT",
      "bank_name": "UNION",
      "account_number": "672202065729294",
      "balance": 5296.59
    },
    {
      "transaction_date": "2023-10-23",
      "description": "ATM WDL 518381\nKASARAGOD",
      "amount": 500.0,
      "transaction_type": "DEBIT",
      "bank_name": "UNION",
      "account_number": "672202065729294",
      "balance": 5796.59
    },
    {
      "transaction_date": "2023-10-21",
      "description": "UPIAR/378645059776/DR/PRIYA\nKUMAR/PRIYA/HDFC/priyak456@okhdfcbank",
      "amount": 4282.0,
      "transaction_type": "DEBIT",
      "bank_name": "UNION",
      "account_number": "672202065729294",
      "balance": 10078.59
    },
    {
      "transaction_date": "2023-10-20",
      "description": "UPIAR/925666470658/DR/BPCL Fuel/BPCL/CNRB/bpcl@canara",
      "amount": 1617.0,
      "transaction_type": "DEBIT",
      "bank_name": "UNION",
      "account_number": "672202065729294",
      "balance": 11695.59
    },
    {
      "transaction_date": "2023-10-20",
      "description": "UPIAR/156983369089/DR/Netflix/NETFLIX/HDFC/netflix@hdfcban\nk",
      "amount": 280.0,
      "transaction_type": "DEBIT",
      "bank_name": "UNION",
      "account_number": "672202065729294",
      "balance": 11975.59
    },
    {
      "transaction_date": "2023-10-20",
      "description": "UPIAR/126860311958/DR/BPCL Fuel/BPCL/CNRB/bpcl@canara",
      "amount": 1004.0,
      "transaction_type": "DEBIT",
      "bank_name": "UNION",
      "account_number": "672202065729294",
      "balance": 12979.59
    }
  ]
}